monasca_events_engine/winchester_dev_test.py
monasca_events_engine/stream_helpers.py
monasca_events_engine/event_processor.py
monasca_events_engine/main.py
monasca_events_engine/event_processor_base.py
monasca_events_engine/pipeline_processor.py
monasca_events_engine/__init__.py
monasca_events_engine/common/__init__.py
monasca_events_engine/common/repositories/constants.py
monasca_events_engine/common/repositories/__init__.py
monasca_events_engine/common/repositories/exceptions.py
monasca_events_engine/common/repositories/mysql/streams_repository.py
monasca_events_engine/common/repositories/mysql/__init__.py
monasca_events_engine/common/repositories/mysql/mysql_repository.py
monasca_events_engine/pipeline_handlers/logging_handler.py
monasca_events_engine/pipeline_handlers/notification_handler.py
monasca_events_engine/pipeline_handlers/__init__.py
monasca_events_engine/tests/first_test.py
monasca_events_engine-0.0.4.dist-info/METADATA
monasca_events_engine-0.0.4.dist-info/entry_points.txt
monasca_events_engine-0.0.4.dist-info/RECORD
monasca_events_engine-0.0.4.dist-info/pbr.json
monasca_events_engine-0.0.4.dist-info/metadata.json
monasca_events_engine-0.0.4.dist-info/DESCRIPTION.rst
monasca_events_engine-0.0.4.dist-info/WHEEL
monasca_events_engine-0.0.4.dist-info/top_level.txt
