Metadata-Version: 2.0
Name: monasca-events-engine
Version: 0.0.4
Summary: Monasca event processing
Home-page: https://github.com/hpcloud-mon/monasca-events-engine
Author: Hewlett-Packard
Author-email: UNKNOWN
License: UNKNOWN
Platform: UNKNOWN
Classifier: Intended Audience :: Information Technology
Classifier: Intended Audience :: System Administrators
Classifier: License :: OSI Approved :: Apache Software License
Classifier: Operating System :: POSIX :: Linux
Classifier: Programming Language :: Python
Classifier: Programming Language :: Python :: 2.7
Requires-Dist: iso8601
Requires-Dist: kafka-python (>=0.9.1,<0.9.3)
Requires-Dist: monasca-statsd
Requires-Dist: python-statsd (>=1.6.3)
Requires-Dist: PyYAML
Requires-Dist: MySQL-python (>=1.2.3)
Requires-Dist: oslo.config (>=1.2.1)
Requires-Dist: oslo.utils
Requires-Dist: oslo.log
Requires-Dist: pbr (>=0.6,!=0.7,<1.0)
Requires-Dist: winchester
